unidt.py
UniDT-0.1.dist-info/METADATA
UniDT-0.1.dist-info/WHEEL
UniDT-0.1.dist-info/entry_points.txt
UniDT-0.1.dist-info/top_level.txt
UniDT-0.1.dist-info/RECORD
